fastperm/__init__.py
fastperm-0.4.dist-info/METADATA
fastperm-0.4.dist-info/WHEEL
fastperm-0.4.dist-info/top_level.txt
fastperm-0.4.dist-info/zip-safe
fastperm-0.4.dist-info/RECORD
